{
  "id": "sojus-dev-env",
  "name": "SOJUS — Desarrollo Local",
  "values": [
    {
      "key": "base_url",
      "value": "http://localhost:8080",
      "type": "default",
      "enabled": true
    },
    {
      "key": "admin_username",
      "value": "admin",
      "type": "default",
      "enabled": true
    },
    {
      "key": "admin_password",
      "value": "admin123",
      "type": "default",
      "enabled": true
    },
    {
      "key": "operador_username",
      "value": "operador",
      "type": "default",
      "enabled": true
    },
    {
      "key": "operador_password",
      "value": "oper123",
      "type": "default",
      "enabled": true
    },
    {
      "key": "tecnico_username",
      "value": "tecnico",
      "type": "default",
      "enabled": true
    },
    {
      "key": "tecnico_password",
      "value": "tec123",
      "type": "default",
      "enabled": true
    }
  ],
  "_postman_variable_scope": "environment"
}
